LICENSE
README.md
setup.py
Felog.egg-info/PKG-INFO
Felog.egg-info/SOURCES.txt
Felog.egg-info/dependency_links.txt
Felog.egg-info/top_level.txt
felog/__init__.py
felog/core.py