Metadata-Version: 2.1
Name: Felog
Version: 1.0.1
Summary: Felog is yet another simple logging library to quickly and simply deploy logging with projects.
Home-page: https://github.com/basegodfelix/felog
Author: Felix Hernandez
License: MIT
License-File: LICENSE
